ruamel.dc2service-0.3.1-py2.7-nspkg.pth
ruamel/dc2service/__init__.py
ruamel/dc2service/__main__.py
ruamel/dc2service/dc2service.py
ruamel/dc2service/template/systemd
ruamel/dc2service/template/upstart
ruamel.dc2service-0.3.1.dist-info/DESCRIPTION.rst
ruamel.dc2service-0.3.1.dist-info/LICENSE.txt
ruamel.dc2service-0.3.1.dist-info/METADATA
ruamel.dc2service-0.3.1.dist-info/RECORD
ruamel.dc2service-0.3.1.dist-info/WHEEL
ruamel.dc2service-0.3.1.dist-info/entry_points.txt
ruamel.dc2service-0.3.1.dist-info/metadata.json
ruamel.dc2service-0.3.1.dist-info/namespace_packages.txt
ruamel.dc2service-0.3.1.dist-info/top_level.txt
