Metadata-Version: 2.0
Name: ruamel.dc2service
Version: 0.3.1
Summary: generate init configuration file (systemd/Upstart) from docker-compose.yml
Home-page: https://bitbucket.org/ruamel/dc2service
Author: Anthon van der Neut
Author-email: a.van.der.neut@ruamel.eu
License: MIT license
Keywords: docker-compose upstart systemd init service
Platform: UNKNOWN
Classifier: Development Status :: 4 - Beta
Classifier: Intended Audience :: Developers
Classifier: License :: OSI Approved :: MIT License
Classifier: Operating System :: OS Independent
Classifier: Programming Language :: Python
Requires-Dist: ruamel.appconfig
Requires-Dist: ruamel.std.argparse
Requires-Dist: ruamel.std.pathlib
Requires-Dist: ruamel.yaml
